django_chunk_file_upload/__init__.py
django_chunk_file_upload/admin.py
django_chunk_file_upload/app_settings.py
django_chunk_file_upload/apps.py
django_chunk_file_upload/constants.py
django_chunk_file_upload/forms.py
django_chunk_file_upload/models.py
django_chunk_file_upload/optimize.py
django_chunk_file_upload/permissions.py
django_chunk_file_upload/typed.py
django_chunk_file_upload/urls.py
django_chunk_file_upload/utils.py
django_chunk_file_upload/views.py
django_chunk_file_upload/widgets.py
django_chunk_file_upload/migrations/0001_initial.py
django_chunk_file_upload/migrations/0002_alter_filemanager_options_and_more.py
django_chunk_file_upload/migrations/0003_rename_file_manager_checksum_idx_filemanager_checksum_idx.py
django_chunk_file_upload/migrations/__init__.py
django_chunk_file_upload/static/css/sweetalert2.min.css
django_chunk_file_upload/static/css/toastr.min.css
django_chunk_file_upload/static/css/upload.chunk.css
django_chunk_file_upload/static/js/jquery-3.7.1.min.js
django_chunk_file_upload/static/js/spark-md5.min.js
django_chunk_file_upload/static/js/sweetalert2.min.js
django_chunk_file_upload/static/js/toastr.min.js
django_chunk_file_upload/static/js/upload.chunk.js
django_chunk_file_upload/templates/django_chunk_file_upload/chunked_upload.html
django_chunk_file_upload/templates/django_chunk_file_upload/admin/add_form.html
django_chunk_file_upload/templates/django_chunk_file_upload/admin/base_form.html
django_chunk_file_upload/templates/django_chunk_file_upload/admin/change_form.html
django_chunk_file_upload/templates/django_chunk_file_upload/admin/submit_line.html
django_chunk_file_upload/templates/django_chunk_file_upload/forms/widgets/drag_drop_input.html
tests/__init__.py
tests/settings.py
tests/test_models.py
tests/urls.py
django_chunk_file_upload-1.0.9.dist-info/AUTHORS
django_chunk_file_upload-1.0.9.dist-info/LICENSE
django_chunk_file_upload-1.0.9.dist-info/METADATA
django_chunk_file_upload-1.0.9.dist-info/WHEEL
django_chunk_file_upload-1.0.9.dist-info/top_level.txt
django_chunk_file_upload-1.0.9.dist-info/RECORD
