Metadata-Version: 2.1
Name: django-chunk-file-upload
Version: 1.0.9
Summary: Django Chunk File Upload is an alternative utility that helps you easily Django's chunked, drag and drop file uploads.
Home-page: https://github.com/thewebscraping/django-chunk-file-upload
Author: Tu Pham
Author-email: thetwofarm@gmail.com
License: MIT
Project-URL: Changelog, https://github.com/thewebscraping/django-chunk-file-upload/blob/main/CHANGELOG.rst
Project-URL: Source, https://github.com/thewebscraping/django-chunk-file-upload
Keywords: python,django,django-chunk-file-upload,django-chunk-upload,django-chunked-upload,django-drag-and-drop-file,django-dropzone,django-file,django-file-manager,django-file-upload,drag-and-drop,drag-drop
Classifier: Development Status :: 5 - Production/Stable
Classifier: Intended Audience :: Developers
Classifier: Topic :: Software Development :: Libraries :: Python Modules
Classifier: Environment :: Web Environment
Classifier: Topic :: Internet
Classifier: License :: OSI Approved :: MIT License
Classifier: Operating System :: OS Independent
Classifier: Programming Language :: Python
Classifier: Programming Language :: Python :: 3
Classifier: Programming Language :: Python :: 3.9
Classifier: Programming Language :: Python :: 3.10
Classifier: Programming Language :: Python :: 3.11
Classifier: Programming Language :: Python :: 3.12
Classifier: Framework :: Django
Classifier: Framework :: Django :: 3.2
Classifier: Framework :: Django :: 4.2
Classifier: Framework :: Django :: 5.0
Requires-Python: >=3.9
License-File: LICENSE
License-File: AUTHORS
Requires-Dist: Django>=3.2
Requires-Dist: pillow>=10.4.0
